{
    "products":[
        {"ten":"Đèn chùm","gia":"2000000"},
        {"ten":"Đèn âm trần","gia":"1500000"},
        {"ten":"Đèn thả trần","gia":"1200000"},
        {"ten":"Đèn cây","gia":"500000"},
        {"ten":"Đèn bàn","gia":"250000"}
    ],
    "categorys":[
        {"ten":"Đèn chùm","gia":"2000000"},
        {"ten":"Đèn âm trần","gia":"1500000"},
        {"ten":"Đèn thả trần","gia":"1200000"},
        {"ten":"Đèn cây","gia":"500000"},
        {"ten":"Đèn bàn","gia":"250000"}
    ],
    "menus":[
        {"ten":"Đèn chùm","gia":"2000000"},
        {"ten":"Đèn âm trần","gia":"1500000"},
        {"ten":"Đèn thả trần","gia":"1200000"},
        {"ten":"Đèn cây","gia":"500000"},
        {"ten":"Đèn bàn","gia":"250000"}
    ],
    "sliders":[
        {"ten":"Đèn chùm","gia":"2000000"},
        {"ten":"Đèn âm trần","gia":"1500000"},
        {"ten":"Đèn thả trần","gia":"1200000"},
        {"ten":"Đèn cây","gia":"500000"},
        {"ten":"Đèn bàn","gia":"250000"}
    ]
} 